{"data_regions":{"regions":[{"id":"L-1","title":"354.46 M2","status":"0","status_text":"VENDIDO","link":""},{"id":"L-10","title":"300 M2","status":"0","status_text":"VENDIDO","link":""},{"id":"L-100","title":"300 M2","status":"0","status_text":"VENDIDO","link":""},{"id":"L-101","title":"300 M2","status":"0","status_text":"VENDIDO","link":""},{"id":"L-102","title":"452.45 M2","status":"0","status_text":"VENDIDO","link":""},{"id":"L-103","title":"346.4 M2","status":"0","status_text":"VENDIDO","link":""},{"id":"L-104","title":"300 M2","status":"0","status_text":"VENDIDO","link":""},{"id":"L-105","title":"300 M2","status":"0","status_text":"VENDIDO","link":""},{"id":"L-106","title":"300 M2","status":"1","status_text":"DISPONIBLE","link":""},{"id":"L-107","title":"300 M2","status":"1","status_text":"DISPONIBLE","link":""},{"id":"L-108","title":"300 M2","status":"1","status_text":"DISPONIBLE","link":""},{"id":"L-109","title":"300 M2","status":"1","status_text":"DISPONIBLE","link":""},{"id":"L-11","title":"300 M2","status":"1","status_text":"DISPONIBLE","link":""},{"id":"L-110","title":"300 M2","status":"1","status_text":"DISPONIBLE","link":""},{"id":"L-111","title":"300 M2","status":"1","status_text":"DISPONIBLE","link":""},{"id":"L-112","title":"300 M2","status":"1","status_text":"DISPONIBLE","link":""},{"id":"L-113","title":"300 M2","status":"1","status_text":"DISPONIBLE","link":""},{"id":"L-114","title":"300 M2","status":"1","status_text":"DISPONIBLE","link":""},{"id":"L-115","title":"300 M2","status":"0","status_text":"VENDIDO","link":""},{"id":"L-116","title":"300 M2","status":"0","status_text":"VENDIDO","link":""},{"id":"L-117","title":"300 M2","status":"1","status_text":"DISPONIBLE","link":""},{"id":"L-118","title":"300 M2","status":"0","status_text":"VENDIDO","link":""},{"id":"L-119","title":"300 M2","status":"0","status_text":"VENDIDO","link":""},{"id":"L-12","title":"300 M2","status":"1","status_text":"DISPONIBLE","link":""},{"id":"L-120","title":"300 M2","status":"0","status_text":"VENDIDO","link":""},{"id":"L-121","title":"650.75 M2","status":"0","status_text":"VENDIDO","link":""},{"id":"L-122","title":"465.58 M2","status":"0","status_text":"VENDIDO","link":""},{"id":"L-123","title":"300 M2","status":"0","status_text":"VENDIDO","link":""},{"id":"L-124","title":"300 M2","status":"1","status_text":"DISPONIBLE","link":""},{"id":"L-125","title":"300 M2","status":"1","status_text":"DISPONIBLE","link":""},{"id":"L-126","title":"300 M2","status":"0","status_text":"VENDIDO","link":""},{"id":"L-127","title":"459.02 M2","status":"0","status_text":"VENDIDO","link":""},{"id":"L-128","title":"346.21 M2","status":"0","status_text":"VENDIDO","link":""},{"id":"L-129","title":"300 M2","status":"0","status_text":"VENDIDO","link":""},{"id":"L-13","title":"300 M2","status":"1","status_text":"DISPONIBLE","link":""},{"id":"L-130","title":"300 M2","status":"1","status_text":"DISPONIBLE","link":""},{"id":"L-131","title":"300 M2","status":"1","status_text":"DISPONIBLE","link":""},{"id":"L-132","title":"300 M2","status":"1","status_text":"DISPONIBLE","link":""},{"id":"L-133","title":"undefined","status":"1","status_text":"DISPONIBLE","link":""},{"id":"L-134","title":"300 M2","status":"1","status_text":"DISPONIBLE","link":""},{"id":"L-135","title":"300 M2","status":"1","status_text":"DISPONIBLE","link":""},{"id":"L-136","title":"300 M2","status":"1","status_text":"DISPONIBLE","link":""},{"id":"L-137","title":"300 M2","status":"1","status_text":"DISPONIBLE","link":""},{"id":"L-138","title":"300 M2","status":"1","status_text":"DISPONIBLE","link":""},{"id":"L-139","title":"300 M2","status":"1","status_text":"DISPONIBLE","link":""},{"id":"L-14","title":"300 M2","status":"1","status_text":"DISPONIBLE","link":""},{"id":"L-140","title":"412.39 M2","status":"0","status_text":"VENDIDO","link":""},{"id":"L-141","title":"379.66 M2","status":"0","status_text":"VENDIDO","link":""},{"id":"L-142","title":"300 M2","status":"1","status_text":"DISPONIBLE","link":""},{"id":"L-143","title":"300 M2","status":"1","status_text":"DISPONIBLE","link":""},{"id":"L-144","title":"300 M2","status":"1","status_text":"DISPONIBLE","link":""},{"id":"L-145","title":"300 M2","status":"1","status_text":"DISPONIBLE","link":""},{"id":"L-146","title":"300 M2","status":"1","status_text":"DISPONIBLE","link":""},{"id":"L-147","title":"300 M2","status":"1","status_text":"DISPONIBLE","link":""},{"id":"L-148","title":"300 M2","status":"0","status_text":"VENDIDO","link":""},{"id":"L-149","title":"300 M2","status":"1","status_text":"DISPONIBLE","link":""},{"id":"L-15","title":"300 M2","status":"1","status_text":"DISPONIBLE","link":""},{"id":"L-150","title":"300 M2","status":"1","status_text":"DISPONIBLE","link":""},{"id":"L-151","title":"undefined","status":"1","status_text":"DISPONIBLE","link":""},{"id":"L-152","title":"undefined","status":"1","status_text":"DISPONIBLE","link":""},{"id":"L-153","title":"300 M2","status":"1","status_text":"DISPONIBLE","link":""},{"id":"L-154","title":"300 M2","status":"1","status_text":"DISPONIBLE","link":""},{"id":"L-155","title":"917.85 M2","status":"0","status_text":"VENDIDO","link":""},{"id":"L-156","title":"349.18 M2","status":"0","status_text":"VENDIDO","link":""},{"id":"L-157","title":"323.97 M2","status":"1","status_text":"DISPONIBLE","link":""},{"id":"L-158","title":"","status":"0","status_text":"VENDIDO","link":""},{"id":"L-159","title":"343.38 M2","status":"0","status_text":"VENDIDO","link":""},{"id":"L-16","title":"300 M2","status":"0","status_text":"VENDIDO","link":""},{"id":"L-160","title":"341.23 M2","status":"0","status_text":"VENDIDO","link":""},{"id":"L-161","title":"334.45 M2","status":"0","status_text":"VENDIDO","link":""},{"id":"L-162","title":"324.3 M2","status":"0","status_text":"VENDIDO","link":""},{"id":"L-163","title":"316.22 M2","status":"0","status_text":"VENDIDO","link":""},{"id":"L-164","title":"311.39 M2","status":"0","status_text":"VENDIDO","link":""},{"id":"L-165","title":"309.81 M2","status":"0","status_text":"VENDIDO","link":""},{"id":"L-166","title":"311.51 M2","status":"0","status_text":"VENDIDO","link":""},{"id":"L-167","title":"315.82 M2","status":"1","status_text":"DISPONIBLE","link":""},{"id":"L-168","title":"321.55 M2","status":"0","status_text":"VENDIDO","link":""},{"id":"L-169","title":"384.21 M2","status":"0","status_text":"VENDIDO","link":""},{"id":"L-17","title":"300 M2","status":"0","status_text":"VENDIDO","link":""},{"id":"L-170","title":"394.76 M2","status":"0","status_text":"VENDIDO","link":""},{"id":"L-171","title":"310.94 M2","status":"0","status_text":"VENDIDO","link":""},{"id":"L-172","title":"304.64 M2","status":"0","status_text":"VENDIDO","link":""},{"id":"L-173","title":"303.55 M2","status":"0","status_text":"VENDIDO","link":""},{"id":"L-174","title":"307.32 M2","status":"0","status_text":"VENDIDO","link":""},{"id":"L-175","title":"315.97 M2","status":"0","status_text":"VENDIDO","link":""},{"id":"L-176","title":"433.09 M2","status":"0","status_text":"VENDIDO","link":""},{"id":"L-177","title":"1182.26 M2","status":"0","status_text":"VENDIDO","link":""},{"id":"L-178","title":"300 M2","status":"0","status_text":"VENDIDO","link":""},{"id":"L-179","title":"300 M2","status":"0","status_text":"VENDIDO","link":""},{"id":"L-18","title":"446.26 M2","status":"0","status_text":"VENDIDO","link":""},{"id":"L-180","title":"300 M2","status":"0","status_text":"VENDIDO","link":""},{"id":"L-181","title":"300 M2","status":"0","status_text":"VENDIDO","link":""},{"id":"L-182","title":"300 M2","status":"1","status_text":"DISPONIBLE","link":""},{"id":"L-183","title":"300 M2","status":"1","status_text":"DISPONIBLE","link":""},{"id":"L-184","title":"300 M2","status":"1","status_text":"DISPONIBLE","link":""},{"id":"L-185","title":"300 M2","status":"1","status_text":"DISPONIBLE","link":""},{"id":"L-186","title":"300 M2","status":"1","status_text":"DISPONIBLE","link":""},{"id":"L-187","title":"360.96 M2","status":"0","status_text":"VENDIDO","link":""},{"id":"L-19","title":"512.21 M2","status":"0","status_text":"VENDIDO","link":""},{"id":"L-2","title":"351.29 M2","status":"0","status_text":"VENDIDO","link":""},{"id":"L-20","title":"300 M2","status":"1","status_text":"DISPONIBLE","link":""},{"id":"L-21","title":"300 M2","status":"1","status_text":"DISPONIBLE","link":""},{"id":"L-22","title":"300 M2","status":"1","status_text":"DISPONIBLE","link":""},{"id":"L-23","title":"300 M2","status":"1","status_text":"DISPONIBLE","link":""},{"id":"L-24","title":"300 M2","status":"1","status_text":"DISPONIBLE","link":""},{"id":"L-25","title":"300 M2","status":"1","status_text":"DISPONIBLE","link":""},{"id":"L-26","title":"300 M2","status":"1","status_text":"DISPONIBLE","link":""},{"id":"L-27","title":"300 M2","status":"1","status_text":"DISPONIBLE","link":""},{"id":"L-28","title":"300 M2","status":"1","status_text":"DISPONIBLE","link":""},{"id":"L-29","title":"300 M2","status":"1","status_text":"DISPONIBLE","link":""},{"id":"L-3","title":"344.18 M2","status":"0","status_text":"VENDIDO","link":""},{"id":"L-30","title":"300 M2","status":"1","status_text":"DISPONIBLE","link":""},{"id":"L-31","title":"300 M2","status":"1","status_text":"DISPONIBLE","link":""},{"id":"L-32","title":"1114.53 M2","status":"0","status_text":"VENDIDO","link":""},{"id":"L-33","title":"395.62 M2","status":"0","status_text":"VENDIDO","link":""},{"id":"L-34","title":"337.5 M2","status":"1","status_text":"DISPONIBLE","link":""},{"id":"L-35","title":"337.5 M2","status":"1","status_text":"DISPONIBLE","link":""},{"id":"L-36","title":"337.5 M2","status":"0","status_text":"VENDIDO","link":""},{"id":"L-37","title":"324 M2","status":"1","status_text":"DISPONIBLE","link":""},{"id":"L-38","title":"324 M2","status":"1","status_text":"DISPONIBLE","link":""},{"id":"L-39","title":"324 M2","status":"1","status_text":"DISPONIBLE","link":""},{"id":"L-4","title":"333.12 M2","status":"0","status_text":"VENDIDO","link":""},{"id":"L-40","title":"324 M2","status":"1","status_text":"DISPONIBLE","link":""},{"id":"L-41","title":"324 M2","status":"0","status_text":"VENDIDO","link":""},{"id":"L-42","title":"643.24 M2","status":"0","status_text":"VENDIDO","link":""},{"id":"L-43","title":"339.54 M2","status":"0","status_text":"VENDIDO","link":""},{"id":"L-44","title":"294 M2","status":"1","status_text":"DISPONIBLE","link":""},{"id":"L-45","title":"294 M2","status":"0","status_text":"VENDIDO","link":""},{"id":"L-46","title":"294 M2","status":"1","status_text":"DISPONIBLE","link":""},{"id":"L-47","title":"294 M2","status":"1","status_text":"DISPONIBLE","link":""},{"id":"L-48","title":"294 M2","status":"1","status_text":"DISPONIBLE","link":""},{"id":"L-49","title":"294 M2","status":"0","status_text":"VENDIDO","link":""},{"id":"L-5","title":"1010.2 M2","status":"0","status_text":"VENDIDO","link":""},{"id":"L-50","title":"421.6 M2","status":"0","status_text":"VENDIDO","link":""},{"id":"L-51","title":"458.54 M2","status":"0","status_text":"VENDIDO","link":""},{"id":"L-52","title":"384.04 M2","status":"0","status_text":"VENDIDO","link":""},{"id":"L-53","title":"349.04 M2","status":"0","status_text":"VENDIDO","link":""},{"id":"L-54","title":"324.06 M2","status":"0","status_text":"VENDIDO","link":""},{"id":"L-55","title":"308.9 M2","status":"0","status_text":"VENDIDO","link":""},{"id":"L-56","title":"303.47 M2","status":"0","status_text":"VENDIDO","link":""},{"id":"L-57","title":"307.71 M2","status":"0","status_text":"VENDIDO","link":""},{"id":"L-58","title":"371.43 M2","status":"0","status_text":"VENDIDO","link":""},{"id":"L-59","title":"465.43 M2","status":"0","status_text":"VENDIDO","link":""},{"id":"L-6","title":"300 M2","status":"1","status_text":"DISPONIBLE","link":""},{"id":"L-60","title":"324 M2","status":"1","status_text":"DISPONIBLE","link":""},{"id":"L-61","title":"324 M2","status":"1","status_text":"DISPONIBLE","link":""},{"id":"L-62","title":"324 M2","status":"1","status_text":"DISPONIBLE","link":""},{"id":"L-63","title":"324 M2","status":"1","status_text":"DISPONIBLE","link":""},{"id":"L-64","title":"324 M2","status":"1","status_text":"DISPONIBLE","link":""},{"id":"L-65","title":"337.5 M2","status":"0","status_text":"VENDIDO","link":""},{"id":"L-66","title":"337.5 M2","status":"0","status_text":"VENDIDO","link":""},{"id":"L-67","title":"652.82 M2","status":"0","status_text":"VENDIDO","link":""},{"id":"L-68","title":"573.93 M2","status":"0","status_text":"VENDIDO","link":""},{"id":"L-69","title":"300 M2","status":"1","status_text":"DISPONIBLE","link":""},{"id":"L-7","title":"300 M2","status":"1","status_text":"DISPONIBLE","link":""},{"id":"L-70","title":"300 M2","status":"1","status_text":"DISPONIBLE","link":""},{"id":"L-71","title":"300 M2","status":"1","status_text":"DISPONIBLE","link":""},{"id":"L-72","title":"300 M2","status":"1","status_text":"DISPONIBLE","link":""},{"id":"L-73","title":"300 M2","status":"0","status_text":"VENDIDO","link":""},{"id":"L-74","title":"300 M2","status":"0","status_text":"VENDIDO","link":""},{"id":"L-75","title":"567.86 M2","status":"0","status_text":"VENDIDO","link":""},{"id":"L-76","title":"460.12 M2","status":"0","status_text":"VENDIDO","link":""},{"id":"L-77","title":"285.66 M2","status":"0","status_text":"VENDIDO","link":""},{"id":"L-78","title":"305.59 M2","status":"0","status_text":"VENDIDO","link":""},{"id":"L-79","title":"317.93 M2","status":"0","status_text":"VENDIDO","link":""},{"id":"L-8","title":"300 M2","status":"0","status_text":"VENDIDO","link":""},{"id":"L-80","title":"322.78 M2","status":"0","status_text":"VENDIDO","link":""},{"id":"L-81","title":"320.16 M2","status":"0","status_text":"VENDIDO","link":""},{"id":"L-82","title":"310.05 M2","status":"0","status_text":"VENDIDO","link":""},{"id":"L-83","title":"292.39 M2","status":"0","status_text":"VENDIDO","link":""},{"id":"L-84","title":"583.92 M2","status":"0","status_text":"VENDIDO","link":""},{"id":"L-85","title":"584.22 M2","status":"0","status_text":"VENDIDO","link":""},{"id":"L-86","title":"312.5 M2","status":"0","status_text":"VENDIDO","link":""},{"id":"L-87","title":"312.5 M2","status":"0","status_text":"VENDIDO","link":""},{"id":"L-88","title":"312.5 M2","status":"0","status_text":"VENDIDO","link":""},{"id":"L-89","title":"312.5 M2","status":"0","status_text":"VENDIDO","link":""},{"id":"L-9","title":"300 M2","status":"1","status_text":"DISPONIBLE","link":""},{"id":"L-90","title":"312.5 M2","status":"1","status_text":"DISPONIBLE","link":""},{"id":"L-91","title":"312.5 M2","status":"0","status_text":"VENDIDO","link":""},{"id":"L-92","title":"312.5 M2","status":"0","status_text":"VENDIDO","link":""},{"id":"L-93","title":"418.13 M2","status":"0","status_text":"VENDIDO","link":""},{"id":"L-94","title":"525.77 M2","status":"0","status_text":"VENDIDO","link":""},{"id":"L-95","title":"300 M2","status":"0","status_text":"VENDIDO","link":""},{"id":"L-96","title":"300 M2","status":"0","status_text":"VENDIDO","link":""},{"id":"L-97","title":"300 M2","status":"1","status_text":"DISPONIBLE","link":""},{"id":"L-98","title":"300 M2","status":"1","status_text":"DISPONIBLE","link":""},{"id":"L-99","title":"300 M2","status":"1","status_text":"DISPONIBLE","link":""}]}}