[{"data-lot":"28416","lot":"AC_62","status":0,"area":"510.49"},{"data-lot":"28417","lot":"AC_63","status":0,"area":"510.49"},{"data-lot":"28418","lot":"AC_64","status":0,"area":"510.49"},{"data-lot":"28419","lot":"AC_65","status":0,"area":"510.49"},{"data-lot":"28420","lot":"AC_66","status":0,"area":"510.49"},{"data-lot":"28421","lot":"AC_67","status":0,"area":"660.92"},{"data-lot":"28422","lot":"AC_68","status":0,"area":"595.12"},{"data-lot":"28423","lot":"AC_69","status":0,"area":"521.15"},{"data-lot":"28424","lot":"AC_70","status":0,"area":"518.11"},{"data-lot":"28425","lot":"AC_71","status":0,"area":"762.12"},{"data-lot":"28426","lot":"AC_72","status":0,"area":"869.08"},{"data-lot":"28427","lot":"AC_73","status":0,"area":"561.92"},{"data-lot":"28428","lot":"675","status":0,"area":"185.55"},{"data-lot":"28429","lot":"676","status":0,"area":"155.36"},{"data-lot":"28430","lot":"677","status":0,"area":"164.86"},{"data-lot":"28431","lot":"678","status":0,"area":"165.41"},{"data-lot":"28432","lot":"679","status":0,"area":"160.31"},{"data-lot":"28433","lot":"680","status":0,"area":"160.31"},{"data-lot":"28434","lot":"681","status":0,"area":"172.95"},{"data-lot":"28435","lot":"682","status":0,"area":"160.00"},{"data-lot":"28436","lot":"683","status":0,"area":"160.00"},{"data-lot":"28437","lot":"684","status":0,"area":"160.00"},{"data-lot":"28438","lot":"685","status":0,"area":"160.00"},{"data-lot":"28439","lot":"686","status":0,"area":"160.00"},{"data-lot":"28440","lot":"687","status":0,"area":"160.00"},{"data-lot":"28441","lot":"688","status":0,"area":"160.00"},{"data-lot":"28442","lot":"689","status":0,"area":"160.00"},{"data-lot":"28443","lot":"690","status":0,"area":"160.00"},{"data-lot":"28444","lot":"691","status":1,"area":"492.36"},{"data-lot":"28445","lot":"692","status":0,"area":"412.73"},{"data-lot":"28446","lot":"693","status":0,"area":"215.56"},{"data-lot":"28447","lot":"694","status":0,"area":"160.00"},{"data-lot":"28448","lot":"695","status":0,"area":"160.00"},{"data-lot":"28449","lot":"696","status":0,"area":"160.00"},{"data-lot":"28450","lot":"697","status":0,"area":"160.00"},{"data-lot":"28451","lot":"698","status":0,"area":"160.00"},{"data-lot":"28452","lot":"699","status":0,"area":"160.00"},{"data-lot":"28453","lot":"700","status":0,"area":"215.19"},{"data-lot":"28454","lot":"701","status":0,"area":"348.02"},{"data-lot":"28455","lot":"702","status":0,"area":"340.76"},{"data-lot":"28456","lot":"703","status":0,"area":"180.83"},{"data-lot":"28457","lot":"704","status":0,"area":"160.00"},{"data-lot":"28458","lot":"705","status":0,"area":"160.00"},{"data-lot":"28459","lot":"706","status":0,"area":"160.00"},{"data-lot":"28460","lot":"707","status":0,"area":"160.00"},{"data-lot":"28461","lot":"708","status":0,"area":"160.00"},{"data-lot":"28462","lot":"709","status":0,"area":"160.00"},{"data-lot":"28463","lot":"710","status":0,"area":"160.00"},{"data-lot":"28464","lot":"711","status":0,"area":"160.00"},{"data-lot":"28465","lot":"712","status":0,"area":"160.00"},{"data-lot":"28466","lot":"713","status":0,"area":"160.00"},{"data-lot":"28467","lot":"714","status":0,"area":"160.00"},{"data-lot":"28468","lot":"715","status":0,"area":"160.00"},{"data-lot":"28469","lot":"716","status":0,"area":"160.00"},{"data-lot":"28470","lot":"717","status":0,"area":"160.00"},{"data-lot":"28471","lot":"718","status":0,"area":"160.00"},{"data-lot":"28472","lot":"719","status":0,"area":"160.00"},{"data-lot":"28473","lot":"720","status":0,"area":"160.00"},{"data-lot":"28474","lot":"721","status":0,"area":"160.00"},{"data-lot":"28475","lot":"722","status":0,"area":"147.91"},{"data-lot":"28476","lot":"723","status":0,"area":"532.92"},{"data-lot":"28477","lot":"724","status":1,"area":"445.38"},{"data-lot":"28478","lot":"725","status":0,"area":"255.05"},{"data-lot":"28479","lot":"726","status":0,"area":"200.00"},{"data-lot":"28480","lot":"727","status":0,"area":"200.00"},{"data-lot":"28481","lot":"728","status":0,"area":"200.00"},{"data-lot":"28482","lot":"729","status":0,"area":"200.00"},{"data-lot":"28483","lot":"730","status":0,"area":"200.00"},{"data-lot":"28484","lot":"731","status":0,"area":"208.20"},{"data-lot":"28485","lot":"732","status":0,"area":"133.12"},{"data-lot":"28486","lot":"733","status":0,"area":"133.12"},{"data-lot":"28487","lot":"734","status":0,"area":"133.12"},{"data-lot":"28488","lot":"735","status":0,"area":"133.12"},{"data-lot":"28489","lot":"736","status":0,"area":"133.12"},{"data-lot":"28490","lot":"737","status":0,"area":"133.12"},{"data-lot":"28491","lot":"738","status":0,"area":"150.93"},{"data-lot":"28492","lot":"739","status":0,"area":"150.65"},{"data-lot":"28493","lot":"740","status":2,"area":"133.12"},{"data-lot":"28494","lot":"741","status":2,"area":"133.12"},{"data-lot":"28495","lot":"742","status":0,"area":"133.12"},{"data-lot":"28496","lot":"743","status":2,"area":"133.12"},{"data-lot":"28497","lot":"744","status":0,"area":"133.12"},{"data-lot":"28498","lot":"745","status":0,"area":"133.12"},{"data-lot":"28499","lot":"746","status":0,"area":"133.12"},{"data-lot":"28500","lot":"747","status":0,"area":"140.30"},{"data-lot":"28501","lot":"748","status":0,"area":"159.70"},{"data-lot":"28502","lot":"749","status":0,"area":"133.12"},{"data-lot":"28503","lot":"750","status":0,"area":"133.12"},{"data-lot":"28504","lot":"751","status":0,"area":"133.12"},{"data-lot":"28505","lot":"752","status":0,"area":"133.12"},{"data-lot":"28506","lot":"753","status":0,"area":"133.12"},{"data-lot":"28507","lot":"754","status":0,"area":"133.12"},{"data-lot":"28508","lot":"755","status":0,"area":"133.12"},{"data-lot":"28509","lot":"756","status":0,"area":"150.93"},{"data-lot":"28510","lot":"757","status":0,"area":"188.66"},{"data-lot":"28511","lot":"758","status":0,"area":"152.14"},{"data-lot":"28512","lot":"759","status":0,"area":"152.14"},{"data-lot":"28513","lot":"760","status":0,"area":"152.14"},{"data-lot":"28514","lot":"761","status":0,"area":"152.14"},{"data-lot":"28515","lot":"762","status":0,"area":"152.14"},{"data-lot":"28516","lot":"763","status":0,"area":"152.14"},{"data-lot":"28517","lot":"764","status":0,"area":"172.43"},{"data-lot":"28518","lot":"765","status":0,"area":"191.83"},{"data-lot":"28519","lot":"766","status":0,"area":"152.14"},{"data-lot":"28520","lot":"767","status":0,"area":"152.14"},{"data-lot":"28521","lot":"768","status":0,"area":"152.14"},{"data-lot":"28522","lot":"769","status":0,"area":"152.14"},{"data-lot":"28523","lot":"770","status":0,"area":"152.14"},{"data-lot":"28524","lot":"771","status":0,"area":"152.14"},{"data-lot":"28525","lot":"772","status":0,"area":"188.93"},{"data-lot":"28526","lot":"773","status":0,"area":"215.51"},{"data-lot":"28527","lot":"774","status":0,"area":"159.21"},{"data-lot":"28528","lot":"775","status":0,"area":"160.00"},{"data-lot":"28529","lot":"776","status":0,"area":"160.00"},{"data-lot":"28530","lot":"777","status":0,"area":"160.00"},{"data-lot":"28531","lot":"778","status":0,"area":"160.00"},{"data-lot":"28532","lot":"779","status":0,"area":"160.00"},{"data-lot":"28533","lot":"780","status":0,"area":"160.00"},{"data-lot":"28534","lot":"781","status":0,"area":"160.00"},{"data-lot":"28535","lot":"782","status":0,"area":"160.00"},{"data-lot":"28536","lot":"783","status":0,"area":"160.00"},{"data-lot":"28537","lot":"784","status":0,"area":"160.00"},{"data-lot":"28538","lot":"785","status":0,"area":"160.00"},{"data-lot":"28539","lot":"786","status":0,"area":"160.00"},{"data-lot":"28540","lot":"787","status":0,"area":"160.00"},{"data-lot":"28541","lot":"788","status":0,"area":"160.00"},{"data-lot":"28542","lot":"789","status":0,"area":"160.00"},{"data-lot":"28543","lot":"790","status":0,"area":"160.00"},{"data-lot":"28544","lot":"791","status":0,"area":"160.00"},{"data-lot":"28545","lot":"792","status":0,"area":"160.00"},{"data-lot":"28546","lot":"793","status":0,"area":"160.00"},{"data-lot":"28547","lot":"794","status":0,"area":"160.00"},{"data-lot":"28548","lot":"795","status":0,"area":"160.00"},{"data-lot":"28549","lot":"796","status":0,"area":"160.00"},{"data-lot":"28550","lot":"797","status":0,"area":"160.00"},{"data-lot":"28551","lot":"798","status":0,"area":"174.34"},{"data-lot":"28552","lot":"799","status":0,"area":"686.11"},{"data-lot":"28553","lot":"800","status":0,"area":"192.08"},{"data-lot":"28554","lot":"801","status":0,"area":"160.00"},{"data-lot":"28555","lot":"802","status":0,"area":"160.00"},{"data-lot":"28556","lot":"803","status":0,"area":"160.00"},{"data-lot":"28557","lot":"804","status":0,"area":"160.00"},{"data-lot":"28558","lot":"805","status":0,"area":"160.00"},{"data-lot":"28559","lot":"806","status":0,"area":"226.57"},{"data-lot":"28560","lot":"807","status":1,"area":"668.61"},{"data-lot":"28561","lot":"808","status":0,"area":"219.75"},{"data-lot":"28562","lot":"809","status":0,"area":"160.00"},{"data-lot":"28563","lot":"810","status":0,"area":"160.00"},{"data-lot":"28564","lot":"811","status":0,"area":"160.00"},{"data-lot":"28565","lot":"812","status":0,"area":"160.00"},{"data-lot":"28566","lot":"813","status":0,"area":"160.00"},{"data-lot":"28567","lot":"814","status":0,"area":"160.00"},{"data-lot":"28568","lot":"815","status":0,"area":"160.00"},{"data-lot":"28569","lot":"816","status":0,"area":"160.00"},{"data-lot":"28570","lot":"817","status":0,"area":"160.00"},{"data-lot":"28571","lot":"818","status":0,"area":"160.00"},{"data-lot":"28572","lot":"819","status":0,"area":"160.00"},{"data-lot":"28573","lot":"820","status":0,"area":"160.00"},{"data-lot":"28574","lot":"821","status":0,"area":"160.00"},{"data-lot":"28575","lot":"822","status":0,"area":"160.00"},{"data-lot":"28576","lot":"823","status":0,"area":"160.00"},{"data-lot":"28577","lot":"824","status":0,"area":"160.00"},{"data-lot":"28578","lot":"825","status":1,"area":"160.00"},{"data-lot":"28579","lot":"826","status":0,"area":"160.00"},{"data-lot":"28580","lot":"827","status":0,"area":"160.00"},{"data-lot":"28581","lot":"828","status":0,"area":"160.00"},{"data-lot":"28582","lot":"829","status":0,"area":"160.00"},{"data-lot":"28583","lot":"830","status":0,"area":"160.00"},{"data-lot":"28584","lot":"831","status":0,"area":"160.00"},{"data-lot":"28585","lot":"832","status":0,"area":"160.00"},{"data-lot":"28586","lot":"833","status":0,"area":"160.00"},{"data-lot":"28587","lot":"834","status":0,"area":"190.77"},{"data-lot":"28588","lot":"835","status":0,"area":"576.62"},{"data-lot":"28589","lot":"836","status":0,"area":"544.07"},{"data-lot":"28590","lot":"837","status":0,"area":"176.54"},{"data-lot":"28591","lot":"838","status":0,"area":"200.00"},{"data-lot":"28592","lot":"839","status":0,"area":"200.00"},{"data-lot":"28593","lot":"840","status":0,"area":"402.54"},{"data-lot":"28594","lot":"841","status":0,"area":"185.08"},{"data-lot":"28595","lot":"842","status":0,"area":"190.00"},{"data-lot":"28596","lot":"843","status":0,"area":"190.00"},{"data-lot":"28597","lot":"844","status":0,"area":"190.00"},{"data-lot":"28598","lot":"845","status":0,"area":"188.65"},{"data-lot":"28599","lot":"846","status":0,"area":"188.65"},{"data-lot":"28600","lot":"847","status":0,"area":"190.00"},{"data-lot":"28601","lot":"848","status":0,"area":"190.00"},{"data-lot":"28602","lot":"849","status":0,"area":"190.00"},{"data-lot":"28603","lot":"850","status":0,"area":"200.52"},{"data-lot":"28604","lot":"851","status":0,"area":"133.00"},{"data-lot":"28605","lot":"852","status":0,"area":"133.00"},{"data-lot":"28606","lot":"853","status":0,"area":"133.00"},{"data-lot":"28607","lot":"854","status":0,"area":"133.00"},{"data-lot":"28608","lot":"855","status":2,"area":"133.00"},{"data-lot":"28609","lot":"856","status":0,"area":"131.65"},{"data-lot":"28610","lot":"857","status":0,"area":"131.65"},{"data-lot":"28611","lot":"858","status":0,"area":"133.00"},{"data-lot":"28612","lot":"859","status":0,"area":"133.00"},{"data-lot":"28613","lot":"860","status":0,"area":"133.00"},{"data-lot":"28614","lot":"861","status":0,"area":"133.00"},{"data-lot":"28615","lot":"862","status":0,"area":"133.00"},{"data-lot":"28616","lot":"863","status":0,"area":"179.85"},{"data-lot":"28617","lot":"864","status":0,"area":"133.00"},{"data-lot":"28618","lot":"865","status":0,"area":"133.00"},{"data-lot":"28619","lot":"866","status":0,"area":"133.00"},{"data-lot":"28620","lot":"867","status":0,"area":"133.00"},{"data-lot":"28621","lot":"868","status":2,"area":"133.00"},{"data-lot":"28622","lot":"869","status":0,"area":"179.11"},{"data-lot":"28623","lot":"870","status":0,"area":"179.11"},{"data-lot":"28624","lot":"871","status":0,"area":"133.00"},{"data-lot":"28625","lot":"872","status":0,"area":"133.00"},{"data-lot":"28627","lot":"874","status":0,"area":"133.00"},{"data-lot":"28628","lot":"875","status":0,"area":"133.00"},{"data-lot":"28629","lot":"876","status":0,"area":"195.29"},{"data-lot":"28630","lot":"877","status":0,"area":"210.47"},{"data-lot":"28631","lot":"878","status":1,"area":"152.00"},{"data-lot":"28632","lot":"879","status":1,"area":"152.00"},{"data-lot":"28633","lot":"880","status":0,"area":"152.00"},{"data-lot":"28634","lot":"881","status":0,"area":"152.00"},{"data-lot":"28635","lot":"882","status":0,"area":"152.00"},{"data-lot":"28636","lot":"883","status":0,"area":"152.00"},{"data-lot":"28637","lot":"884","status":2,"area":"152.00"},{"data-lot":"28638","lot":"885","status":2,"area":"152.00"},{"data-lot":"28639","lot":"886","status":0,"area":"225.91"},{"data-lot":"28640","lot":"887","status":0,"area":"250.00"},{"data-lot":"28641","lot":"888","status":0,"area":"250.00"},{"data-lot":"28642","lot":"889","status":0,"area":"250.00"},{"data-lot":"28643","lot":"890","status":0,"area":"250.00"},{"data-lot":"28644","lot":"891","status":0,"area":"250.00"},{"data-lot":"28645","lot":"892","status":0,"area":"250.00"},{"data-lot":"28646","lot":"893","status":0,"area":"250.00"},{"data-lot":"28647","lot":"894","status":0,"area":"475.30"},{"data-lot":"28648","lot":"895","status":0,"area":"455.13"},{"data-lot":"28649","lot":"896","status":0,"area":"250.00"},{"data-lot":"28650","lot":"897","status":0,"area":"250.00"},{"data-lot":"28651","lot":"898","status":0,"area":"250.00"},{"data-lot":"28652","lot":"899","status":0,"area":"250.00"},{"data-lot":"28653","lot":"900","status":0,"area":"518.15"},{"data-lot":"28654","lot":"901","status":0,"area":"419.66"},{"data-lot":"28655","lot":"902","status":0,"area":"200.00"},{"data-lot":"28656","lot":"903","status":0,"area":"200.00"},{"data-lot":"28670","lot":"917","status":0,"area":"199.56"},{"data-lot":"28671","lot":"918","status":0,"area":"221.44"},{"data-lot":"28672","lot":"919","status":0,"area":"226.91"},{"data-lot":"28673","lot":"920","status":0,"area":"232.37"},{"data-lot":"28674","lot":"921","status":0,"area":"233.83"}]